README
sautils.py
setup.py
sautils.egg-info/PKG-INFO
sautils.egg-info/SOURCES.txt
sautils.egg-info/dependency_links.txt
sautils.egg-info/entry_points.txt
sautils.egg-info/not-zip-safe
sautils.egg-info/requires.txt
sautils.egg-info/top_level.txt