Metadata-Version: 1.0
Name: sautils
Version: 0.3
Summary: Various SQLAlchemy utilities
Home-page: UNKNOWN
Author: Andrey Popp
Author-email: 8mayday@gmail.com
License: BSD
Platform: UNKNOWN
